{"stats":{"minecraft:picked_up":{"minecraft:porkchop":2},"minecraft:killed_by":{"minecraft:vex":2,"minecraft:player":3},"minecraft:dropped":{"minecraft:cooked_beef":38},"minecraft:custom":{"minecraft:jump":846,"minecraft:pig_one_cm":4463,"minecraft:time_since_rest":47629,"minecraft:damage_taken":75368,"minecraft:minecart_one_cm":3217,"minecraft:walk_one_cm":182060,"minecraft:crouch_one_cm":15,"minecraft:leave_game":194,"minecraft:sprint_one_cm":15331,"minecraft:play_time":1660587,"minecraft:time_since_death":47629,"minecraft:walk_on_water_one_cm":3140,"minecraft:deaths":27,"minecraft:total_world_time":2313534,"minecraft:walk_under_water_one_cm":14582,"minecraft:drop":38,"minecraft:fly_one_cm":52204}},"DataVersion":3105}